scripts/__init__.py
scripts/djsearch.py
dj_search_image-0.1.0.dist-info/METADATA
dj_search_image-0.1.0.dist-info/WHEEL
dj_search_image-0.1.0.dist-info/entry_points.txt
dj_search_image-0.1.0.dist-info/top_level.txt
dj_search_image-0.1.0.dist-info/RECORD
