Metadata-Version: 2.1
Name: dj-search-image
Version: 0.1.0
Requires-Dist: click
Requires-Dist: keyboard
Requires-Dist: climage
Requires-Dist: urllib3
Requires-Dist: google-search-results
